pythium/__init__.py
pythium/_impl.py
pythium/actions.py
pythium/appium_desired_caps_sample.py
pythium/assertions.py
pythium/browser.py
pythium/commands.py
pythium/device_tools.py
pythium/emoji.py
pythium/exceptions.py
pythium/http_session.py
pythium/objects.py
pythium/utils.py
pythium-1.1.4.dist-info/LICENSE.txt
pythium-1.1.4.dist-info/METADATA
pythium-1.1.4.dist-info/WHEEL
pythium-1.1.4.dist-info/top_level.txt
pythium-1.1.4.dist-info/RECORD
