Metadata-Version: 2.1
Name: pythium
Version: 1.1.4
Summary: Python based Page Factory.
Home-page: https://github.com/lucas234/pythium
Author: lucas
Author-email: ly_liubo@163.com
License: MIT
Classifier: Intended Audience :: Developers
Classifier: License :: OSI Approved :: MIT License
Classifier: Programming Language :: Python
Classifier: Programming Language :: Python :: 3.7
Classifier: Programming Language :: Python :: 3.8
Classifier: Programming Language :: Python :: 3.9
Classifier: Operating System :: Microsoft :: Windows
Classifier: Operating System :: POSIX :: Linux
Classifier: Operating System :: MacOS :: MacOS X
Classifier: Topic :: Internet :: WWW/HTTP :: Browsers
Classifier: Topic :: Software Development :: Testing
Requires-Python: >=3
License-File: LICENSE.txt
Requires-Dist: selenium (==4.1)
Requires-Dist: Appium-Python-Client (==2.7.1)
Requires-Dist: retrying (==1.3.4)
Requires-Dist: requests (==2.31.0)
Requires-Dist: allure-python-commons (==2.9.43)
Requires-Dist: loguru (==0.5.3)
Requires-Dist: webdriver-manager (==4.0.0)
